CHANGES.txt
LICENSE
MANIFEST.in
README.rst
requirements.txt
setup.py
CoPriNet/__init__.py
CoPriNet/bibtex.py
CoPriNet/constants.py
CoPriNet/objects.py
CoPriNet/protocols/__init__.py
CoPriNet/protocols/protocol_CoPriNet.py
CoPriNet/tests/__init__.py
CoPriNet/viewers/__init__.py
scipion_chem_coprinet.egg-info/PKG-INFO
scipion_chem_coprinet.egg-info/SOURCES.txt
scipion_chem_coprinet.egg-info/dependency_links.txt
scipion_chem_coprinet.egg-info/entry_points.txt
scipion_chem_coprinet.egg-info/requires.txt
scipion_chem_coprinet.egg-info/top_level.txt