Metadata-Version: 2.1
Name: scipion-chem-coprinet
Version: 0.2
Summary: Scipion framework plugin for the use of CoPriNet software tools
Home-page: https://github.com/scipion-chem/scipion-chem-CoPriNet
Author: Verónica Gamo
Author-email: veronica.gamoparejo@usp.ceu.es
Keywords: scipion CoPriNet scipion-3.0 cheminformatics
License-File: LICENSE
Requires-Dist: scipion-em
Requires-Dist: scipion-chem
